LICENSE.txt
README.md
setup.py
./src/pyperspairdiamorse/pyperspairdiamorse.cpp
src/baselib/__init__.py
src/baselib/include/CubicalComplex.hpp
src/baselib/include/MorseVectorField.hpp
src/baselib/include/PackedMap.hpp
src/baselib/include/PersPairExtractor.h
src/baselib/include/SEDT.hpp
src/baselib/include/SimpleComplex.hpp
src/baselib/include/VertexMap.hpp
src/baselib/include/chainComplexExtraction.hpp
src/baselib/include/collections.hpp
src/baselib/include/persistence.hpp
src/baselib/include/restricted.hpp
src/baselib/include/traversals.hpp
src/baselib/include/vectorFieldExtraction.hpp
src/pyperspairdiamorse/pyperspairdiamorse.cpp
src/pyperspairdiamorse.egg-info/PKG-INFO
src/pyperspairdiamorse.egg-info/SOURCES.txt
src/pyperspairdiamorse.egg-info/dependency_links.txt
src/pyperspairdiamorse.egg-info/entry_points.txt
src/pyperspairdiamorse.egg-info/requires.txt
src/pyperspairdiamorse.egg-info/top_level.txt