Metadata-Version: 2.1
Name: pyperspairdiamorse
Version: 0.0.3
Summary: Cross-platform C++ library of persistent pair extractor using the diamorse approach
Home-page: UNKNOWN
Author: Andrey S. Zubov, Kirill M. Gerke, Andrey A. Ananev
Author-email: andrey.ananev@phystech.edu
License: GPLv3
Platform: UNKNOWN
Classifier: Development Status :: 3 - Alpha
Classifier: Intended Audience :: Science/Research
Classifier: Intended Audience :: Education
Classifier: License :: OSI Approved :: GNU Lesser General Public License v3 (LGPLv3)
Classifier: Programming Language :: C++
Classifier: Programming Language :: Python :: 3 :: Only
License-File: LICENSE.txt
